cortopy/_Body.py
cortopy/_Camera.py
cortopy/_Compositing.py
cortopy/_Environment.py
cortopy/_Rendering.py
cortopy/_Shading.py
cortopy/_State.py
cortopy/_Sun.py
cortopy/_Template.py
cortopy/_Utils.py
cortopy/__init__.py
cortopy/_version.py
cortopy-0.1.1.dist-info/LICENSE
cortopy-0.1.1.dist-info/METADATA
cortopy-0.1.1.dist-info/WHEEL
cortopy-0.1.1.dist-info/top_level.txt
cortopy-0.1.1.dist-info/RECORD
