Metadata-Version: 2.2
Name: cortopy
Version: 0.1.1
Summary: Celestial Object Rendering TOol (CORTO) is a bundle of codes that can be used to generate synthetic images-label pairs of celestial bodies.
Home-page: https://github.com/MattiaPugliatti/corto
Author: Mattia Pugliatti
Classifier: Development Status :: 4 - Beta
Classifier: Natural Language :: English
Classifier: Topic :: Scientific/Engineering
Classifier: License :: OSI Approved :: MIT License
Classifier: Programming Language :: Python :: 3.11
Classifier: Operating System :: POSIX :: Linux
Classifier: Operating System :: Microsoft :: Windows
Classifier: Operating System :: MacOS :: MacOS X
Requires-Python: >=3.11
License-File: LICENSE
Requires-Dist: numpy>=1.20.0
Requires-Dist: matplotlib
Requires-Dist: scipy
Requires-Dist: datetime
